redis_bundle/__init__.py
redis_bundle/bundle.py
redis_bundle-0.2.dist-info/DESCRIPTION.rst
redis_bundle-0.2.dist-info/METADATA
redis_bundle-0.2.dist-info/RECORD
redis_bundle-0.2.dist-info/WHEEL
redis_bundle-0.2.dist-info/metadata.json
redis_bundle-0.2.dist-info/top_level.txt
