Metadata-Version: 2.0
Name: redis-bundle
Version: 0.2
Summary: Redis support for applauncher
Home-page: https://github.com/applauncher-team/redis_bundle
Author: Alvaro Garcia Gomez
Author-email: maxpowel@gmail.com
License: UNKNOWN
Download-URL: https://github.com/applauncher-team/redis_bundle/archive/master.zip
Keywords: applauncher,bundle,redis
Platform: UNKNOWN
Classifier: Topic :: Adaptive Technologies
Classifier: Topic :: Software Development
Classifier: Topic :: System
Classifier: Topic :: Utilities
Requires-Dist: redis
